build.py
publish.py
release.py
uvx_release-0.1.2.dist-info/METADATA
uvx_release-0.1.2.dist-info/WHEEL
uvx_release-0.1.2.dist-info/entry_points.txt
uvx_release-0.1.2.dist-info/top_level.txt
uvx_release-0.1.2.dist-info/RECORD
