Metadata-Version: 2.4
Name: uvx-release
Version: 0.1.2
Summary: Temporary shortcut and fix for `uv build/publish` issues
Author-email: Gwang-Jin Kim <gwang.jin.kim.phd@mgail.com>
License: MIT
Keywords: uv,uvx,publish,build,pypirc
Classifier: Programming Language :: Python :: 3
Classifier: License :: OSI Approved :: MIT License
Classifier: Operating System :: OS Independent
Requires-Python: >=3.8
